laravel_oauth2/__init__.py
laravel_oauth2/backends/__init__.py
laravel_oauth2/backends/laravel_oauth2.py
laravel_oauth2-0.1.2.dist-info/METADATA
laravel_oauth2-0.1.2.dist-info/WHEEL
laravel_oauth2-0.1.2.dist-info/RECORD
